yambda/__init__.py
yambda/constants.py
yambda/evaluation/__init__.py
yambda/evaluation/metrics.py
yambda/evaluation/ranking.py
yambda/processing/__init__.py
yambda/processing/chunk_read.py
yambda/processing/timesplit.py
yambda/utils.py
yambda_benchmark-0.1.0.dist-info/LICENSE
yambda_benchmark-0.1.0.dist-info/METADATA
yambda_benchmark-0.1.0.dist-info/WHEEL
yambda_benchmark-0.1.0.dist-info/RECORD
