Metadata-Version: 2.3
Name: yambda-benchmark
Version: 0.1.0
Summary: 
Author: Yandex
Requires-Python: >=3.11
Classifier: Programming Language :: Python :: 3
Classifier: Programming Language :: Python :: 3.11
Classifier: Programming Language :: Python :: 3.12
Classifier: Programming Language :: Python :: 3.13
Requires-Dist: click
Requires-Dist: matplotlib
Requires-Dist: numpy
Requires-Dist: optuna
Requires-Dist: polars-u64-idx (==1.28.1)
Requires-Dist: scipy
Requires-Dist: torch
Requires-Dist: tqdm
Project-URL: Repository, https://github.com/homutov/yambda-benchmark
Project-URL: huggingface, https://huggingface.co/datasets/yandex/yambda
